Metadata-Version: 1.2
Name: youi
Version: 0.0.1
Summary: editable, live python UI
Home-page: UNKNOWN
Author: Daniel Dugas
License: UNKNOWN
Platform: UNKNOWN
Requires-Python: >=3.6
